[
    {
        "title": "Mi primer título",
        "desc": "Descripción del contenido",
        "date": "2024-11-10 15:30:00+00"
    },
    {
        "title": "Mi segundo título",
        "desc": "Descripción del contenido 2",
       "date": "2024-11-10 15:30:00+00"
    },
    {
        "title": "Leo Messi",
        "desc": "Lionel Messi is a football player from Argentina who plays for Inter Miami. He has won the Ballon D'Or, the annual award given to the best player in the world, 8 times, 2022 FIFA World Cup winner and an Olympic gold medal winner in 2008. He was born in 1987 in Rosario, Argentina's third-biggest city.",
        "date": "2024-11-10 15:30:00+00"
    }
      
  ]
  